[
  {
    "company_name": "TechNova Solutions",
    "job_title": "Software Development Intern",
    "responsibilities": [
      "Assist in developing web applications using React and Node.js",
      "Write unit and integration tests",
      "Collaborate with senior developers on feature implementation"
    ],
    "duration": "3 months"
  },
  {
    "company_name": "GreenLeaf Marketing",
    "job_title": "Digital Marketing Assistant",
    "responsibilities": [
      "Create and schedule social media posts",
      "Monitor campaign performance using Google Analytics",
      "Assist in SEO optimization tasks"
    ],
    "duration": "6 months"
  },
  {
    "company_name": "HealthFirst Clinic",
    "job_title": "Administrative Part-time Assistant",
    "responsibilities": [
      "Manage patient appointment scheduling",
      "Maintain electronic medical records",
      "Support front desk operations"
    ],
    "duration": "Part-time (20 hrs/week)"
  },
  {
    "company_name": "EduMentors Inc.",
    "job_title": "Content Writing Intern",
    "responsibilities": [
      "Write blog posts and study materials",
      "Research academic topics across disciplines",
      "Work with the editorial team for content review"
    ],
    "duration": "2 months"
  }
 
]
